{
  "player_name": "Aaron Gordon",
  "player_id": 203932,
  "games_collected": 23,
  "games_data": [
    {
      "game_id": "0022500054",
      "player_id": 203932,
      "player_name": "Aaron Gordon",
      "1Q_PTS": "1",
      "1Q_REB": "2",
      "1Q_AST": "0",
      "1Q_MIN": "3:21",
      "1H_PTS": "1",
      "1H_REB": "2",
      "1H_AST": "0",
      "1H_MIN": "3:21",
      "FULL_PTS": "1",
      "FULL_REB": "2",
      "FULL_AST": "0",
      "FULL_MIN": "3:21"
    },
    {
      "game_id": "0022500248",
      "player_id": 203932,
      "player_name": "Aaron Gordon",
      "1Q_PTS": "10",
      "1Q_REB": "1",
      "1Q_AST": "0",
      "1Q_MIN": "7:55",
      "1H_PTS": "16",
      "1H_REB": "5",
      "1H_AST": "0",
      "1H_MIN": "16:50",
      "FULL_PTS": "24",
      "FULL_REB": "10",
      "FULL_AST": "0",
      "FULL_MIN": "32:25"
    },
    {
      "game_id": "0022500232",
      "player_id": 203932,
      "player_name": "Aaron Gordon",
      "1Q_PTS": "8",
      "1Q_REB": "3",
      "1Q_AST": "0",
      "1Q_MIN": "9:49",
      "1H_PTS": "13",
      "1H_REB": "5",
      "1H_AST": "0",
      "1H_MIN": "18:58",
      "FULL_PTS": "23",
      "FULL_REB": "10",
      "FULL_AST": "1",
      "FULL_MIN": "35:43"
    },
    {
      "game_id": "0022500224",
      "player_id": 203932,
      "player_name": "Aaron Gordon",
      "1Q_PTS": "0",
      "1Q_REB": "1",
      "1Q_AST": "0",
      "1Q_MIN": "8:06",
      "1H_PTS": "12",
      "1H_REB": "3",
      "1H_AST": "0",
      "1H_MIN": "15:42",
      "FULL_PTS": "18",
      "FULL_REB": "5",
      "FULL_AST": "0",
      "FULL_MIN": "30:47"
    },
    {
      "game_id": "0022500212",
      "player_id": 203932,
      "player_name": "Aaron Gordon",
      "1Q_PTS": "4",
      "1Q_REB": "2",
      "1Q_AST": "0",
      "1Q_MIN": "8:12",
      "1H_PTS": "12",
      "1H_REB": "2",
      "1H_AST": "0",
      "1H_MIN": "15:33",
      "FULL_PTS": "17",
      "FULL_REB": "7",
      "FULL_AST": "3",
      "FULL_MIN": "30:09"
    },
    {
      "game_id": "0022500037",
      "player_id": 203932,
      "player_name": "Aaron Gordon",
      "1Q_PTS": "10",
      "1Q_REB": "3",
      "1Q_AST": "0",
      "1Q_MIN": "11:22",
      "1H_PTS": "10",
      "1H_REB": "3",
      "1H_AST": "1",
      "1H_MIN": "15:38",
      "FULL_PTS": "18",
      "FULL_REB": "3",
      "FULL_AST": "1",
      "FULL_MIN": "23:58"
    },
    {
      "game_id": "0022500178",
      "player_id": 203932,
      "player_name": "Aaron Gordon",
      "1Q_PTS": "6",
      "1Q_REB": "1",
      "1Q_AST": "1",
      "1Q_MIN": "8:12",
      "1H_PTS": "17",
      "1H_REB": "3",
      "1H_AST": "1",
      "1H_MIN": "16:04",
      "FULL_PTS": "24",
      "FULL_REB": "6",
      "FULL_AST": "1",
      "FULL_MIN": "30:50"
    },
    {
      "game_id": "0022500162",
      "player_id": 203932,
      "player_name": "Aaron Gordon",
      "1Q_PTS": "10",
      "1Q_REB": "4",
      "1Q_AST": "0",
      "1Q_MIN": "7:51",
      "1H_PTS": "15",
      "1H_REB": "5",
      "1H_AST": "0",
      "1H_MIN": "14:45",
      "FULL_PTS": "20",
      "FULL_REB": "7",
      "FULL_AST": "1",
      "FULL_MIN": "30:15"
    },
    {
      "game_id": "0022500026",
      "player_id": 203932,
      "player_name": "Aaron Gordon",
      "1Q_PTS": "4",
      "1Q_REB": "2",
      "1Q_AST": "0",
      "1Q_MIN": "9:50",
      "1H_PTS": "8",
      "1H_REB": "3",
      "1H_AST": "1",
      "1H_MIN": "15:35",
      "FULL_PTS": "14",
      "FULL_REB": "5",
      "FULL_AST": "1",
      "FULL_MIN": "31:40"
    },
    {
      "game_id": "0022500134",
      "player_id": 203932,
      "player_name": "Aaron Gordon",
      "1Q_PTS": "4",
      "1Q_REB": "4",
      "1Q_AST": "2",
      "1Q_MIN": "9:39",
      "1H_PTS": "6",
      "1H_REB": "7",
      "1H_AST": "3",
      "1H_MIN": "17:15",
      "FULL_PTS": "9",
      "FULL_REB": "9",
      "FULL_AST": "3",
      "FULL_MIN": "22:31"
    },
    {
      "game_id": "0022500008",
      "player_id": 203932,
      "player_name": "Aaron Gordon",
      "1Q_PTS": "7",
      "1Q_REB": "1",
      "1Q_AST": "0",
      "1Q_MIN": "6:51",
      "1H_PTS": "9",
      "1H_REB": "2",
      "1H_AST": "0",
      "1H_MIN": "16:29",
      "FULL_PTS": "9",
      "FULL_REB": "3",
      "FULL_AST": "3",
      "FULL_MIN": "32:49"
    },
    {
      "game_id": "0022500104",
      "player_id": 203932,
      "player_name": "Aaron Gordon",
      "1Q_PTS": "4",
      "1Q_REB": "0",
      "1Q_AST": "0",
      "1Q_MIN": "7:26",
      "1H_PTS": "13",
      "1H_REB": "2",
      "1H_AST": "0",
      "1H_MIN": "13:45",
      "FULL_PTS": "17",
      "FULL_REB": "2",
      "FULL_AST": "1",
      "FULL_MIN": "25:12"
    },
    {
      "game_id": "0022500006",
      "player_id": 203932,
      "player_name": "Aaron Gordon",
      "1Q_PTS": "11",
      "1Q_REB": "2",
      "1Q_AST": "1",
      "1Q_MIN": "9:52",
      "1H_PTS": "25",
      "1H_REB": "2",
      "1H_AST": "1",
      "1H_MIN": "15:58",
      "FULL_PTS": "45",
      "FULL_REB": "7",
      "FULL_AST": "2",
      "FULL_MIN": "33:39"
    },
    {
      "game_id": "0022500640",
      "player_id": 203932,
      "player_name": "Aaron Gordon",
      "1Q_PTS": 7,
      "1Q_REB": 3,
      "1Q_AST": 2,
      "1Q_MIN": "8:36",
      "1H_PTS": 13,
      "1H_REB": 6,
      "1H_AST": 3,
      "1H_MIN": "16:06"
    },
    {
      "game_id": "0022500629",
      "player_id": 203932,
      "player_name": "Aaron Gordon",
      "1Q_PTS": 8,
      "1Q_REB": 2,
      "1Q_AST": 1,
      "1Q_MIN": "8:06",
      "1H_PTS": 8,
      "1H_REB": 4,
      "1H_AST": 3,
      "1H_MIN": "16:07"
    },
    {
      "game_id": "0022500617",
      "player_id": 203932,
      "player_name": "Aaron Gordon",
      "1Q_PTS": 1,
      "1Q_REB": 0,
      "1Q_AST": 1,
      "1Q_MIN": "7:27",
      "1H_PTS": 7,
      "1H_REB": 1,
      "1H_AST": 1,
      "1H_MIN": "14:53"
    },
    {
      "game_id": "0022500600",
      "player_id": 203932,
      "player_name": "Aaron Gordon",
      "1Q_PTS": 2,
      "1Q_REB": 3,
      "1Q_AST": 3,
      "1Q_MIN": "7:41",
      "1H_PTS": 3,
      "1H_REB": 4,
      "1H_AST": 5,
      "1H_MIN": "15:19"
    },
    {
      "game_id": "0022500575",
      "player_id": 203932,
      "player_name": "Aaron Gordon",
      "1Q_PTS": 5,
      "1Q_REB": 2,
      "1Q_AST": 1,
      "1Q_MIN": "7:15",
      "1H_PTS": 9,
      "1H_REB": 4,
      "1H_AST": 3,
      "1H_MIN": "14:41"
    },
    {
      "game_id": "0022500567",
      "player_id": 203932,
      "player_name": "Aaron Gordon",
      "1Q_PTS": 2,
      "1Q_REB": 1,
      "1Q_AST": 1,
      "1Q_MIN": "7:01",
      "1H_PTS": 8,
      "1H_REB": 1,
      "1H_AST": 1,
      "1H_MIN": "14:39"
    },
    {
      "game_id": "0022500554",
      "player_id": 203932,
      "player_name": "Aaron Gordon",
      "1Q_PTS": 6,
      "1Q_REB": 2,
      "1Q_AST": 0,
      "1Q_MIN": "7:29",
      "1H_PTS": 14,
      "1H_REB": 3,
      "1H_AST": 2,
      "1H_MIN": "15:14"
    },
    {
      "game_id": "0022500537",
      "player_id": 203932,
      "player_name": "Aaron Gordon",
      "1Q_PTS": 5,
      "1Q_REB": 1,
      "1Q_AST": 2,
      "1Q_MIN": "6:52",
      "1H_PTS": 12,
      "1H_REB": 5,
      "1H_AST": 3,
      "1H_MIN": "14:10"
    },
    {
      "game_id": "0022500520",
      "player_id": 203932,
      "player_name": "Aaron Gordon",
      "1Q_PTS": 2,
      "1Q_REB": 0,
      "1Q_AST": 1,
      "1Q_MIN": "4:31",
      "1H_PTS": 9,
      "1H_REB": 4,
      "1H_AST": 1,
      "1H_MIN": "12:51"
    },
    {
      "game_id": "0022500496",
      "player_id": 203932,
      "player_name": "Aaron Gordon",
      "1Q_PTS": 7,
      "1Q_REB": 1,
      "1Q_AST": 0,
      "1Q_MIN": "4:32",
      "1H_PTS": 13,
      "1H_REB": 2,
      "1H_AST": 0,
      "1H_MIN": "12:29"
    }
  ],
  "last_updated": "2026-01-30T08:31:30.934462",
  "1Q_PTS_avg": 5.391304347826087,
  "1Q_REB_avg": 1.7826086956521738,
  "1Q_AST_avg": 0.6956521739130435,
  "1H_PTS_avg": 11.0,
  "1H_REB_avg": 3.391304347826087,
  "1H_AST_avg": 1.2608695652173914,
  "FULL_PTS_avg": 18.384615384615383,
  "FULL_REB_avg": 5.846153846153846,
  "FULL_AST_avg": 1.3076923076923077,
  "1H_PTS_ratio": 0.598326359832636,
  "1Q_PTS_ratio": 0.29325086410769513,
  "1H_REB_ratio": 0.5800915331807781,
  "1Q_REB_ratio": 0.3049199084668192,
  "1H_AST_ratio": 0.9641943734015346,
  "1Q_AST_ratio": 0.5319693094629155
}