{
  "player_name": "Evan Mobley",
  "player_id": 1630596,
  "games_collected": 30,
  "games_data": [
    {
      "game_id": "0022500510",
      "player_id": 1630596,
      "player_name": "Evan Mobley",
      "1Q_PTS": "6",
      "1Q_REB": "3",
      "1Q_AST": "1",
      "1Q_MIN": "9:27",
      "1H_PTS": "9",
      "1H_REB": "3",
      "1H_AST": "1",
      "1H_MIN": "16:20",
      "FULL_PTS": "20",
      "FULL_REB": "6",
      "FULL_AST": "5",
      "FULL_MIN": "35:36"
    },
    {
      "game_id": "0022500494",
      "player_id": 1630596,
      "player_name": "Evan Mobley",
      "1Q_PTS": "6",
      "1Q_REB": "1",
      "1Q_AST": "1",
      "1Q_MIN": "7:42",
      "1H_PTS": "11",
      "1H_REB": "2",
      "1H_AST": "3",
      "1H_MIN": "13:31",
      "FULL_PTS": "15",
      "FULL_REB": "4",
      "FULL_AST": "5",
      "FULL_MIN": "32:45"
    },
    {
      "game_id": "0022500478",
      "player_id": 1630596,
      "player_name": "Evan Mobley",
      "1Q_PTS": "6",
      "1Q_REB": "4",
      "1Q_AST": "1",
      "1Q_MIN": "9:09",
      "1H_PTS": "8",
      "1H_REB": "5",
      "1H_AST": "3",
      "1H_MIN": "15:50",
      "FULL_PTS": "8",
      "FULL_REB": "11",
      "FULL_AST": "4",
      "FULL_MIN": "32:17"
    },
    {
      "game_id": "0022500465",
      "player_id": 1630596,
      "player_name": "Evan Mobley",
      "1Q_PTS": "6",
      "1Q_REB": "3",
      "1Q_AST": "1",
      "1Q_MIN": "6:50",
      "1H_PTS": "11",
      "1H_REB": "7",
      "1H_AST": "3",
      "1H_MIN": "15:33",
      "FULL_PTS": "16",
      "FULL_REB": "10",
      "FULL_AST": "5",
      "FULL_MIN": "28:40"
    },
    {
      "game_id": "0022500456",
      "player_id": 1630596,
      "player_name": "Evan Mobley",
      "1Q_PTS": "2",
      "1Q_REB": "2",
      "1Q_AST": "0",
      "1Q_MIN": "7:21",
      "1H_PTS": "4",
      "1H_REB": "4",
      "1H_AST": "2",
      "1H_MIN": "14:00",
      "FULL_PTS": "16",
      "FULL_REB": "7",
      "FULL_AST": "2",
      "FULL_MIN": "28:38"
    },
    {
      "game_id": "0022500438",
      "player_id": 1630596,
      "player_name": "Evan Mobley",
      "1Q_PTS": "2",
      "1Q_REB": "2",
      "1Q_AST": "1",
      "1Q_MIN": "5:36",
      "1H_PTS": "4",
      "1H_REB": "3",
      "1H_AST": "1",
      "1H_MIN": "11:30",
      "FULL_PTS": "4",
      "FULL_REB": "4",
      "FULL_AST": "2",
      "FULL_MIN": "20:04"
    },
    {
      "game_id": "0022500009",
      "player_id": 1630596,
      "player_name": "Evan Mobley",
      "1Q_PTS": "2",
      "1Q_REB": "1",
      "1Q_AST": "0",
      "1Q_MIN": "5:08",
      "1H_PTS": "10",
      "1H_REB": "3",
      "1H_AST": "1",
      "1H_MIN": "11:21",
      "FULL_PTS": "14",
      "FULL_REB": "9",
      "FULL_AST": "3",
      "FULL_MIN": "25:19"
    },
    {
      "game_id": "0022501212",
      "player_id": 1630596,
      "player_name": "Evan Mobley",
      "1Q_PTS": "10",
      "1Q_REB": "1",
      "1Q_AST": "2",
      "1Q_MIN": "6:55",
      "1H_PTS": "18",
      "1H_REB": "6",
      "1H_AST": "4",
      "1H_MIN": "16:21",
      "FULL_PTS": "23",
      "FULL_REB": "13",
      "FULL_AST": "6",
      "FULL_MIN": "36:14"
    },
    {
      "game_id": "0022500352",
      "player_id": 1630596,
      "player_name": "Evan Mobley",
      "1Q_PTS": "6",
      "1Q_REB": "3",
      "1Q_AST": "0",
      "1Q_MIN": "6:55",
      "1H_PTS": "10",
      "1H_REB": "5",
      "1H_AST": "0",
      "1H_MIN": "16:43",
      "FULL_PTS": "18",
      "FULL_REB": "10",
      "FULL_AST": "1",
      "FULL_MIN": "35:08"
    },
    {
      "game_id": "0022500341",
      "player_id": 1630596,
      "player_name": "Evan Mobley",
      "1Q_PTS": "4",
      "1Q_REB": "2",
      "1Q_AST": "1",
      "1Q_MIN": "7:43",
      "1H_PTS": "13",
      "1H_REB": "4",
      "1H_AST": "1",
      "1H_MIN": "16:34",
      "FULL_PTS": "17",
      "FULL_REB": "10",
      "FULL_AST": "5",
      "FULL_MIN": "32:18"
    },
    {
      "game_id": "0022500324",
      "player_id": 1630596,
      "player_name": "Evan Mobley",
      "1Q_PTS": "12",
      "1Q_REB": "2",
      "1Q_AST": "1",
      "1Q_MIN": "6:46",
      "1H_PTS": "16",
      "1H_REB": "3",
      "1H_AST": "2",
      "1H_MIN": "15:50",
      "FULL_PTS": "23",
      "FULL_REB": "10",
      "FULL_AST": "5",
      "FULL_MIN": "34:47"
    },
    {
      "game_id": "0022500310",
      "player_id": 1630596,
      "player_name": "Evan Mobley",
      "1Q_PTS": "8",
      "1Q_REB": "1",
      "1Q_AST": "1",
      "1Q_MIN": "8:05",
      "1H_PTS": "11",
      "1H_REB": "3",
      "1H_AST": "3",
      "1H_MIN": "16:33",
      "FULL_PTS": "13",
      "FULL_REB": "5",
      "FULL_AST": "5",
      "FULL_MIN": "28:12"
    },
    {
      "game_id": "0022500302",
      "player_id": 1630596,
      "player_name": "Evan Mobley",
      "1Q_PTS": "4",
      "1Q_REB": "4",
      "1Q_AST": "1",
      "1Q_MIN": "9:49",
      "1H_PTS": "10",
      "1H_REB": "6",
      "1H_AST": "2",
      "1H_MIN": "17:24",
      "FULL_PTS": "27",
      "FULL_REB": "14",
      "FULL_AST": "4",
      "FULL_MIN": "38:40"
    },
    {
      "game_id": "0022500069",
      "player_id": 1630596,
      "player_name": "Evan Mobley",
      "1Q_PTS": "3",
      "1Q_REB": "3",
      "1Q_AST": "1",
      "1Q_MIN": "9:42",
      "1H_PTS": "7",
      "1H_REB": "9",
      "1H_AST": "2",
      "1H_MIN": "16:15",
      "FULL_PTS": "20",
      "FULL_REB": "14",
      "FULL_AST": "7",
      "FULL_MIN": "33:39"
    },
    {
      "game_id": "0022500284",
      "player_id": 1630596,
      "player_name": "Evan Mobley",
      "1Q_PTS": "5",
      "1Q_REB": "1",
      "1Q_AST": "1",
      "1Q_MIN": "9:17",
      "1H_PTS": "8",
      "1H_REB": "3",
      "1H_AST": "2",
      "1H_MIN": "16:21",
      "FULL_PTS": "14",
      "FULL_REB": "5",
      "FULL_AST": "4",
      "FULL_MIN": "31:11"
    },
    {
      "game_id": "0022500278",
      "player_id": 1630596,
      "player_name": "Evan Mobley",
      "1Q_PTS": "2",
      "1Q_REB": "3",
      "1Q_AST": "0",
      "1Q_MIN": "10:11",
      "1H_PTS": "6",
      "1H_REB": "4",
      "1H_AST": "1",
      "1H_MIN": "18:56",
      "FULL_PTS": "18",
      "FULL_REB": "10",
      "FULL_AST": "2",
      "FULL_MIN": "34:21"
    },
    {
      "game_id": "0022500048",
      "player_id": 1630596,
      "player_name": "Evan Mobley",
      "1Q_PTS": "12",
      "1Q_REB": "2",
      "1Q_AST": "0",
      "1Q_MIN": "10:16",
      "1H_PTS": "12",
      "1H_REB": "5",
      "1H_AST": "2",
      "1H_MIN": "17:33",
      "FULL_PTS": "22",
      "FULL_REB": "12",
      "FULL_AST": "4",
      "FULL_MIN": "34:50"
    },
    {
      "game_id": "0022500255",
      "player_id": 1630596,
      "player_name": "Evan Mobley",
      "1Q_PTS": "5",
      "1Q_REB": "0",
      "1Q_AST": "0",
      "1Q_MIN": "9:42",
      "1H_PTS": "10",
      "1H_REB": "2",
      "1H_AST": "0",
      "1H_MIN": "17:55",
      "FULL_PTS": "18",
      "FULL_REB": "6",
      "FULL_AST": "0",
      "FULL_MIN": "35:41"
    },
    {
      "game_id": "0022500241",
      "player_id": 1630596,
      "player_name": "Evan Mobley",
      "1Q_PTS": "3",
      "1Q_REB": "1",
      "1Q_AST": "1",
      "1Q_MIN": "7:52",
      "1H_PTS": "7",
      "1H_REB": "2",
      "1H_AST": "3",
      "1H_MIN": "16:23",
      "FULL_PTS": "14",
      "FULL_REB": "6",
      "FULL_AST": "6",
      "FULL_MIN": "36:03"
    },
    {
      "game_id": "0022500228",
      "player_id": 1630596,
      "player_name": "Evan Mobley",
      "1Q_PTS": "6",
      "1Q_REB": "0",
      "1Q_AST": "1",
      "1Q_MIN": "8:51",
      "1H_PTS": "11",
      "1H_REB": "3",
      "1H_AST": "1",
      "1H_MIN": "15:00",
      "FULL_PTS": "22",
      "FULL_REB": "13",
      "FULL_AST": "4",
      "FULL_MIN": "35:19"
    },
    {
      "game_id": "0022500658",
      "player_id": 1630596,
      "player_name": "Evan Mobley",
      "1Q_PTS": 8,
      "1Q_REB": 0,
      "1Q_AST": 0,
      "1Q_MIN": "9:19",
      "1H_PTS": 13,
      "1H_REB": 1,
      "1H_AST": 0,
      "1H_MIN": "16:14"
    },
    {
      "game_id": "0022500646",
      "player_id": 1630596,
      "player_name": "Evan Mobley",
      "1Q_PTS": 4,
      "1Q_REB": 0,
      "1Q_AST": 1,
      "1Q_MIN": "8:40",
      "1H_PTS": 8,
      "1H_REB": 0,
      "1H_AST": 2,
      "1H_MIN": "17:57"
    },
    {
      "game_id": "0022500638",
      "player_id": 1630596,
      "player_name": "Evan Mobley",
      "1Q_PTS": 13,
      "1Q_REB": 2,
      "1Q_AST": 2,
      "1Q_MIN": "8:34",
      "1H_PTS": 19,
      "1H_REB": 5,
      "1H_AST": 2,
      "1H_MIN": "17:16"
    },
    {
      "game_id": "0022500620",
      "player_id": 1630596,
      "player_name": "Evan Mobley",
      "1Q_PTS": 7,
      "1Q_REB": 4,
      "1Q_AST": 0,
      "1Q_MIN": "7:40",
      "1H_PTS": 13,
      "1H_REB": 11,
      "1H_AST": 0,
      "1H_MIN": "18:18"
    },
    {
      "game_id": "0022500015",
      "player_id": 1630596,
      "player_name": "Evan Mobley",
      "1Q_PTS": 8,
      "1Q_REB": 2,
      "1Q_AST": 1,
      "1Q_MIN": "9:55",
      "1H_PTS": 10,
      "1H_REB": 5,
      "1H_AST": 2,
      "1H_MIN": "14:45"
    },
    {
      "game_id": "0022500589",
      "player_id": 1630596,
      "player_name": "Evan Mobley",
      "1Q_PTS": 7,
      "1Q_REB": 1,
      "1Q_AST": 1,
      "1Q_MIN": "9:38",
      "1H_PTS": 7,
      "1H_REB": 3,
      "1H_AST": 2,
      "1H_MIN": "18:20"
    },
    {
      "game_id": "0022500572",
      "player_id": 1630596,
      "player_name": "Evan Mobley",
      "1Q_PTS": 4,
      "1Q_REB": 4,
      "1Q_AST": 1,
      "1Q_MIN": "9:45",
      "1H_PTS": 13,
      "1H_REB": 9,
      "1H_AST": 4,
      "1H_MIN": "19:30"
    },
    {
      "game_id": "0022500558",
      "player_id": 1630596,
      "player_name": "Evan Mobley",
      "1Q_PTS": 0,
      "1Q_REB": 0,
      "1Q_AST": 0,
      "1Q_MIN": "7:38",
      "1H_PTS": 2,
      "1H_REB": 5,
      "1H_AST": 5,
      "1H_MIN": "15:44"
    },
    {
      "game_id": "0022500542",
      "player_id": 1630596,
      "player_name": "Evan Mobley",
      "1Q_PTS": 6,
      "1Q_REB": 0,
      "1Q_AST": 1,
      "1Q_MIN": "9:30",
      "1H_PTS": 8,
      "1H_REB": 0,
      "1H_AST": 3,
      "1H_MIN": "17:25"
    },
    {
      "game_id": "0022500530",
      "player_id": 1630596,
      "player_name": "Evan Mobley",
      "1Q_PTS": 4,
      "1Q_REB": 0,
      "1Q_AST": 1,
      "1Q_MIN": "8:50",
      "1H_PTS": 12,
      "1H_REB": 1,
      "1H_AST": 2,
      "1H_MIN": "16:30"
    }
  ],
  "last_updated": "2026-01-30T10:16:45.876981",
  "1Q_PTS_avg": 5.7,
  "1Q_REB_avg": 1.7333333333333334,
  "1Q_AST_avg": 0.7666666666666667,
  "1H_PTS_avg": 10.033333333333333,
  "1H_REB_avg": 4.066666666666666,
  "1H_AST_avg": 1.9666666666666666,
  "FULL_PTS_avg": 17.1,
  "FULL_REB_avg": 8.95,
  "FULL_AST_avg": 3.95,
  "1H_PTS_ratio": 0.5867446393762182,
  "1Q_PTS_ratio": 0.3333333333333333,
  "1H_REB_ratio": 0.4543761638733706,
  "1Q_REB_ratio": 0.1936685288640596,
  "1H_AST_ratio": 0.49789029535864976,
  "1Q_AST_ratio": 0.19409282700421943
}