{
  "player_name": "Tyler Herro",
  "player_id": 1629639,
  "games_collected": 10,
  "games_data": [
    {
      "game_id": "0022500580",
      "player_id": 1629639,
      "player_name": "Tyler Herro",
      "1Q_PTS": 7,
      "1Q_REB": 0,
      "1Q_AST": 1,
      "1Q_MIN": "8:42",
      "1H_PTS": 15,
      "1H_REB": 0,
      "1H_AST": 2,
      "1H_MIN": "13:28"
    },
    {
      "game_id": "0022500564",
      "player_id": 1629639,
      "player_name": "Tyler Herro",
      "1Q_PTS": 7,
      "1Q_REB": 0,
      "1Q_AST": 2,
      "1Q_MIN": "7:38",
      "1H_PTS": 14,
      "1H_REB": 2,
      "1H_AST": 3,
      "1H_MIN": "17:43"
    },
    {
      "game_id": "0022500553",
      "player_id": 1629639,
      "player_name": "Tyler Herro",
      "1Q_PTS": 8,
      "1Q_REB": 1,
      "1Q_AST": 2,
      "1Q_MIN": "8:43",
      "1H_PTS": 8,
      "1H_REB": 1,
      "1H_AST": 2,
      "1H_MIN": "11:05"
    },
    {
      "game_id": "0022500543",
      "player_id": 1629639,
      "player_name": "Tyler Herro",
      "1Q_PTS": 2,
      "1Q_REB": 2,
      "1Q_AST": 0,
      "1Q_MIN": "10:11",
      "1H_PTS": 10,
      "1H_REB": 4,
      "1H_AST": 2,
      "1H_MIN": "17:14"
    },
    {
      "game_id": "0022500513",
      "player_id": 1629639,
      "player_name": "Tyler Herro",
      "1Q_PTS": 3,
      "1Q_REB": 4,
      "1Q_AST": 1,
      "1Q_MIN": "5:33",
      "1H_PTS": 10,
      "1H_REB": 6,
      "1H_AST": 2,
      "1H_MIN": "14:11"
    },
    {
      "game_id": "0022501201",
      "player_id": 1629639,
      "player_name": "Tyler Herro",
      "1Q_PTS": 9,
      "1Q_REB": 2,
      "1Q_AST": 0,
      "1Q_MIN": "7:56",
      "1H_PTS": 12,
      "1H_REB": 4,
      "1H_AST": 1,
      "1H_MIN": "16:40"
    },
    {
      "game_id": "0022500332",
      "player_id": 1629639,
      "player_name": "Tyler Herro",
      "1Q_PTS": 12,
      "1Q_REB": 3,
      "1Q_AST": 0,
      "1Q_MIN": "9:30",
      "1H_PTS": 20,
      "1H_REB": 3,
      "1H_AST": 0,
      "1H_MIN": "17:04"
    },
    {
      "game_id": "0022500313",
      "player_id": 1629639,
      "player_name": "Tyler Herro",
      "1Q_PTS": 5,
      "1Q_REB": 2,
      "1Q_AST": 0,
      "1Q_MIN": "8:57",
      "1H_PTS": 8,
      "1H_REB": 2,
      "1H_AST": 0,
      "1H_MIN": "13:01"
    },
    {
      "game_id": "0022500296",
      "player_id": 1629639,
      "player_name": "Tyler Herro",
      "1Q_PTS": 0,
      "1Q_REB": 0,
      "1Q_AST": 0,
      "1Q_MIN": "9:29",
      "1H_PTS": 10,
      "1H_REB": 1,
      "1H_AST": 0,
      "1H_MIN": "17:29"
    },
    {
      "game_id": "0022500062",
      "player_id": 1629639,
      "player_name": "Tyler Herro",
      "1Q_PTS": 7,
      "1Q_REB": 2,
      "1Q_AST": 2,
      "1Q_MIN": "8:14",
      "1H_PTS": 9,
      "1H_REB": 3,
      "1H_AST": 3,
      "1H_MIN": "13:45"
    }
  ],
  "1Q_PTS_avg": 6.0,
  "1Q_REB_avg": 1.6,
  "1Q_AST_avg": 0.8,
  "1H_PTS_avg": 11.6,
  "1H_REB_avg": 2.6,
  "1H_AST_avg": 1.5
}